{
    "swagger": "2.0",
    "info": {
        "description": "SlotFinder API Doc",
        "title": "SlotFinder API",
        "contact": {
            "email": "contact@zide.fr"
        },
        "version": "1.0b"
    },
    "paths": {
        "/api/v1/account": {
            "post": {
                "description": "Create a new account with the provided parameters.",
                "consumes": [
                    "application/json"
                ],
                "produces": [
                    "application/json"
                ],
                "tags": [
                    "Account"
                ],
                "summary": "Create an account",
                "parameters": [
                    {
                        "description": "Account parameters",
                        "name": "data",
                        "in": "body",
                        "required": true,
                        "schema": {
                            "$ref": "#/definitions/account.AccountCreateDto"
                        }
                    }
                ],
                "responses": {
                    "200": {
                        "description": "OK"
                    },
                    "400": {
                        "description": "Bad Request",
                        "schema": {
                            "$ref": "#/definitions/helpers.ApiError"
                        }
                    }
                }
            },
            "patch": {
                "security": [
                    {
                        "AccessTokenCookie": []
                    }
                ],
                "description": "Update own account",
                "consumes": [
                    "application/json"
                ],
                "produces": [
                    "application/json"
                ],
                "tags": [
                    "Account"
                ],
                "summary": "Update my account",
                "parameters": [
                    {
                        "description": "Account parameters",
                        "name": "data",
                        "in": "body",
                        "required": true,
                        "schema": {
                            "$ref": "#/definitions/account.AccountUpdateDto"
                        }
                    }
                ],
                "responses": {
                    "200": {
                        "description": "OK",
                        "schema": {
                            "$ref": "#/definitions/model.Account"
                        }
                    },
                    "400": {
                        "description": "Bad Request",
                        "schema": {
                            "$ref": "#/definitions/helpers.ApiError"
                        }
                    }
                }
            }
        },
        "/api/v1/account/me": {
            "get": {
                "security": [
                    {
                        "AccessTokenCookie": []
                    }
                ],
                "description": "Get the account information of the current user.",
                "consumes": [
                    "application/json"
                ],
                "produces": [
                    "application/json"
                ],
                "tags": [
                    "Account"
                ],
                "summary": "Get My Account",
                "responses": {
                    "200": {
                        "description": "OK",
                        "schema": {
                            "$ref": "#/definitions/model.Account"
                        }
                    },
                    "400": {
                        "description": "Bad Request",
                        "schema": {
                            "$ref": "#/definitions/helpers.ApiError"
                        }
                    }
                }
            }
        },
        "/api/v1/auth/logout": {
            "post": {
                "security": [
                    {
                        "AccessTokenCookie": []
                    }
                ],
                "consumes": [
                    "application/json"
                ],
                "produces": [
                    "application/json"
                ],
                "tags": [
                    "Authentication"
                ],
                "summary": "Logout",
                "responses": {
                    "200": {
                        "description": "OK"
                    },
                    "401": {
                        "description": "Unauthorized",
                        "schema": {
                            "$ref": "#/definitions/helpers.ApiError"
                        }
                    }
                }
            }
        },
        "/api/v1/auth/signin": {
            "post": {
                "description": "Sign in with email and password",
                "consumes": [
                    "application/json"
                ],
                "produces": [
                    "application/json"
                ],
                "tags": [
                    "Authentication"
                ],
                "summary": "Sign in",
                "parameters": [
                    {
                        "description": "Sign in parameters",
                        "name": "data",
                        "in": "body",
                        "required": true,
                        "schema": {
                            "$ref": "#/definitions/signin.SigninDto"
                        }
                    }
                ],
                "responses": {
                    "200": {
                        "description": "OK",
                        "schema": {
                            "$ref": "#/definitions/signin.TokenResponseDto"
                        }
                    },
                    "400": {
                        "description": "Bad Request",
                        "schema": {
                            "$ref": "#/definitions/helpers.ApiError"
                        }
                    }
                }
            }
        },
        "/api/v1/auth/status": {
            "get": {
                "consumes": [
                    "application/json"
                ],
                "produces": [
                    "application/json"
                ],
                "tags": [
                    "Authentication"
                ],
                "summary": "Status Check",
                "responses": {
                    "200": {
                        "description": "OK"
                    },
                    "401": {
                        "description": "Unauthorized",
                        "schema": {
                            "$ref": "#/definitions/helpers.ApiError"
                        }
                    }
                }
            }
        },
        "/api/v1/auth/{provider}/url": {
            "get": {
                "tags": [
                    "Authentication"
                ],
                "summary": "Get redirect URL for OAuth provider",
                "parameters": [
                    {
                        "enum": [
                            "google",
                            "github",
                            "discord"
                        ],
                        "type": "string",
                        "description": "OAuth provider",
                        "name": "provider",
                        "in": "path",
                        "required": true
                    },
                    {
                        "type": "string",
                        "description": "URL to return to after OAuth",
                        "name": "returnUrl",
                        "in": "query"
                    }
                ],
                "responses": {
                    "200": {
                        "description": "OAuth URL",
                        "schema": {
                            "type": "string"
                        }
                    },
                    "400": {
                        "description": "Bad Request",
                        "schema": {
                            "$ref": "#/definitions/helpers.ApiError"
                        }
                    }
                }
            }
        },
        "/api/v1/availabilities/{availabilityId}": {
            "delete": {
                "security": [
                    {
                        "BearerAuth": []
                    }
                ],
                "consumes": [
                    "application/json"
                ],
                "produces": [
                    "application/json"
                ],
                "tags": [
                    "Availability"
                ],
                "summary": "Delete an availability",
                "parameters": [
                    {
                        "type": "string",
                        "description": "Availability ID",
                        "name": "availabilityId",
                        "in": "path",
                        "required": true
                    }
                ],
                "responses": {
                    "200": {
                        "description": "OK"
                    },
                    "400": {
                        "description": "Bad Request",
                        "schema": {
                            "$ref": "#/definitions/helpers.ApiError"
                        }
                    }
                }
            },
            "patch": {
                "security": [
                    {
                        "BearerAuth": []
                    }
                ],
                "consumes": [
                    "application/json"
                ],
                "produces": [
                    "application/json"
                ],
                "tags": [
                    "Availability"
                ],
                "summary": "Update an availability",
                "parameters": [
                    {
                        "type": "string",
                        "description": "Availability ID",
                        "name": "availabilityId",
                        "in": "path",
                        "required": true
                    },
                    {
                        "description": "Availability parameters",
                        "name": "data",
                        "in": "body",
                        "required": true,
                        "schema": {
                            "$ref": "#/definitions/availability.AvailabilityUpdateDto"
                        }
                    }
                ],
                "responses": {
                    "200": {
                        "description": "OK",
                        "schema": {
                            "$ref": "#/definitions/model.Availability"
                        }
                    },
                    "400": {
                        "description": "Bad Request",
                        "schema": {
                            "$ref": "#/definitions/helpers.ApiError"
                        }
                    }
                }
            }
        },
        "/api/v1/events": {
            "get": {
                "security": [
                    {
                        "BearerAuth": []
                    }
                ],
                "consumes": [
                    "application/json"
                ],
                "produces": [
                    "application/json"
                ],
                "tags": [
                    "Event"
                ],
                "summary": "Get user events",
                "responses": {
                    "200": {
                        "description": "OK",
                        "schema": {
                            "type": "array",
                            "items": {
                                "$ref": "#/definitions/event.EventResponse"
                            }
                        }
                    },
                    "400": {
                        "description": "Bad Request",
                        "schema": {
                            "$ref": "#/definitions/helpers.ApiError"
                        }
                    }
                }
            },
            "post": {
                "security": [
                    {
                        "BearerAuth": []
                    }
                ],
                "consumes": [
                    "application/json"
                ],
                "produces": [
                    "application/json"
                ],
                "tags": [
                    "Event"
                ],
                "summary": "Create an event",
                "parameters": [
                    {
                        "description": "Event parameters",
                        "name": "data",
                        "in": "body",
                        "required": true,
                        "schema": {
                            "$ref": "#/definitions/event.EventCreateDto"
                        }
                    }
                ],
                "responses": {
                    "200": {
                        "description": "OK",
                        "schema": {
                            "$ref": "#/definitions/model.Event"
                        }
                    },
                    "400": {
                        "description": "Bad Request",
                        "schema": {
                            "$ref": "#/definitions/helpers.ApiError"
                        }
                    }
                }
            }
        },
        "/api/v1/events/{eventId}": {
            "get": {
                "consumes": [
                    "application/json"
                ],
                "produces": [
                    "application/json"
                ],
                "tags": [
                    "Event"
                ],
                "summary": "Get event",
                "parameters": [
                    {
                        "type": "string",
                        "description": "Event Id",
                        "name": "eventId",
                        "in": "path",
                        "required": true
                    }
                ],
                "responses": {
                    "200": {
                        "description": "OK",
                        "schema": {
                            "$ref": "#/definitions/event.EventResponse"
                        }
                    },
                    "400": {
                        "description": "Bad Request",
                        "schema": {
                            "$ref": "#/definitions/helpers.ApiError"
                        }
                    }
                }
            }
        },
        "/api/v1/events/{eventId}/availability": {
            "post": {
                "security": [
                    {
                        "BearerAuth": []
                    }
                ],
                "consumes": [
                    "application/json"
                ],
                "produces": [
                    "application/json"
                ],
                "tags": [
                    "Availability"
                ],
                "summary": "Create an availability",
                "parameters": [
                    {
                        "type": "string",
                        "description": "Event ID",
                        "name": "eventId",
                        "in": "path",
                        "required": true
                    },
                    {
                        "description": "Availability parameters",
                        "name": "data",
                        "in": "body",
                        "required": true,
                        "schema": {
                            "$ref": "#/definitions/availability.AvailabilityCreateDto"
                        }
                    }
                ],
                "responses": {
                    "200": {
                        "description": "OK",
                        "schema": {
                            "$ref": "#/definitions/model.Availability"
                        }
                    },
                    "400": {
                        "description": "Bad Request",
                        "schema": {
                            "$ref": "#/definitions/helpers.ApiError"
                        }
                    }
                }
            }
        },
        "/api/v1/events/{eventId}/join": {
            "post": {
                "security": [
                    {
                        "BearerAuth": []
                    }
                ],
                "consumes": [
                    "application/json"
                ],
                "produces": [
                    "application/json"
                ],
                "tags": [
                    "Event"
                ],
                "summary": "Join event",
                "parameters": [
                    {
                        "type": "string",
                        "description": "Event Id",
                        "name": "eventId",
                        "in": "path",
                        "required": true
                    }
                ],
                "responses": {
                    "200": {
                        "description": "OK"
                    },
                    "400": {
                        "description": "Bad Request",
                        "schema": {
                            "$ref": "#/definitions/helpers.ApiError"
                        }
                    }
                }
            }
        },
        "/api/v1/slots/{slotId}/confirm": {
            "post": {
                "security": [
                    {
                        "BearerAuth": []
                    }
                ],
                "consumes": [
                    "application/json"
                ],
                "produces": [
                    "application/json"
                ],
                "tags": [
                    "Slot"
                ],
                "summary": "Confirm a slot",
                "parameters": [
                    {
                        "type": "string",
                        "description": "Slot Id",
                        "name": "slotId",
                        "in": "path",
                        "required": true
                    },
                    {
                        "description": "Confirm Slot parameters",
                        "name": "data",
                        "in": "body",
                        "required": true,
                        "schema": {
                            "$ref": "#/definitions/slot.ConfirmSlotDto"
                        }
                    }
                ],
                "responses": {
                    "200": {
                        "description": "OK",
                        "schema": {
                            "$ref": "#/definitions/model.Slot"
                        }
                    },
                    "400": {
                        "description": "Bad Request",
                        "schema": {
                            "$ref": "#/definitions/helpers.ApiError"
                        }
                    }
                }
            }
        }
    },
    "definitions": {
        "account.AccountCreateDto": {
            "type": "object",
            "required": [
                "email",
                "password",
                "username"
            ],
            "properties": {
                "email": {
                    "type": "string"
                },
                "password": {
                    "type": "string"
                },
                "username": {
                    "type": "string"
                }
            }
        },
        "account.AccountUpdateDto": {
            "type": "object",
            "properties": {
                "email": {
                    "type": "string"
                },
                "password": {
                    "type": "string"
                },
                "username": {
                    "type": "string"
                }
            }
        },
        "availability.AvailabilityCreateDto": {
            "type": "object",
            "required": [
                "endsAt",
                "startsAt"
            ],
            "properties": {
                "endsAt": {
                    "type": "string"
                },
                "startsAt": {
                    "type": "string"
                }
            }
        },
        "availability.AvailabilityUpdateDto": {
            "type": "object",
            "properties": {
                "endsAt": {
                    "type": "string"
                },
                "startsAt": {
                    "type": "string"
                }
            }
        },
        "constants.EventStatus": {
            "type": "string",
            "enum": [
                "IN_DECISION",
                "UPCOMING",
                "FINISHED"
            ],
            "x-enum-varnames": [
                "EVENT_STATUS_IN_DECISION",
                "EVENT_STATUS_UPCOMING",
                "EVENT_STATUS_FINISHED"
            ]
        },
        "constants.Provider": {
            "type": "string",
            "enum": [
                "google",
                "discord",
                "github"
            ],
            "x-enum-varnames": [
                "PROVIDER_GOOGLE",
                "PROVIDER_DISCORD",
                "PROVIDER_GITHUB"
            ]
        },
        "event.EventCreateDto": {
            "type": "object",
            "required": [
                "duration",
                "endsAt",
                "name",
                "startsAt"
            ],
            "properties": {
                "description": {
                    "type": "string"
                },
                "duration": {
                    "type": "integer",
                    "maximum": 30240,
                    "minimum": 15
                },
                "endsAt": {
                    "type": "string"
                },
                "name": {
                    "type": "string"
                },
                "startsAt": {
                    "type": "string"
                }
            }
        },
        "event.EventResponse": {
            "type": "object",
            "properties": {
                "availabilities": {
                    "type": "array",
                    "items": {
                        "$ref": "#/definitions/model.Availability"
                    }
                },
                "createdAt": {
                    "type": "string"
                },
                "description": {
                    "type": "string"
                },
                "duration": {
                    "description": "In minutes",
                    "type": "integer"
                },
                "endsAt": {
                    "type": "string"
                },
                "id": {
                    "type": "string"
                },
                "name": {
                    "type": "string"
                },
                "owner": {
                    "description": "Relations",
                    "allOf": [
                        {
                            "$ref": "#/definitions/model.Account"
                        }
                    ]
                },
                "participants": {
                    "type": "array",
                    "items": {
                        "$ref": "#/definitions/model.Account"
                    }
                },
                "slots": {
                    "type": "array",
                    "items": {
                        "$ref": "#/definitions/model.Slot"
                    }
                },
                "startsAt": {
                    "type": "string"
                },
                "status": {
                    "$ref": "#/definitions/constants.EventStatus"
                }
            }
        },
        "helpers.ApiError": {
            "type": "object",
            "properties": {
                "code": {
                    "type": "string"
                }
            }
        },
        "model.Account": {
            "type": "object",
            "properties": {
                "avatarUrl": {
                    "type": "string"
                },
                "createdAt": {
                    "type": "string"
                },
                "email": {
                    "type": "string"
                },
                "events": {
                    "type": "array",
                    "items": {
                        "$ref": "#/definitions/model.AccountEvent"
                    }
                },
                "id": {
                    "type": "string"
                },
                "providers": {
                    "type": "array",
                    "items": {
                        "$ref": "#/definitions/model.AccountProvider"
                    }
                },
                "userName": {
                    "type": "string"
                }
            }
        },
        "model.AccountEvent": {
            "type": "object",
            "properties": {
                "account": {
                    "description": "Relations",
                    "allOf": [
                        {
                            "$ref": "#/definitions/model.Account"
                        }
                    ]
                },
                "createdAt": {
                    "type": "string"
                },
                "event": {
                    "$ref": "#/definitions/model.Event"
                }
            }
        },
        "model.AccountProvider": {
            "type": "object",
            "properties": {
                "provider": {
                    "$ref": "#/definitions/constants.Provider"
                }
            }
        },
        "model.Availability": {
            "type": "object",
            "properties": {
                "account": {
                    "$ref": "#/definitions/model.Account"
                },
                "endsAt": {
                    "type": "string"
                },
                "id": {
                    "type": "string"
                },
                "startsAt": {
                    "type": "string"
                }
            }
        },
        "model.Event": {
            "type": "object",
            "properties": {
                "availabilities": {
                    "type": "array",
                    "items": {
                        "$ref": "#/definitions/model.Availability"
                    }
                },
                "createdAt": {
                    "type": "string"
                },
                "description": {
                    "type": "string"
                },
                "duration": {
                    "description": "In minutes",
                    "type": "integer"
                },
                "endsAt": {
                    "type": "string"
                },
                "id": {
                    "type": "string"
                },
                "name": {
                    "type": "string"
                },
                "owner": {
                    "description": "Relations",
                    "allOf": [
                        {
                            "$ref": "#/definitions/model.Account"
                        }
                    ]
                },
                "slots": {
                    "type": "array",
                    "items": {
                        "$ref": "#/definitions/model.Slot"
                    }
                },
                "startsAt": {
                    "type": "string"
                },
                "status": {
                    "$ref": "#/definitions/constants.EventStatus"
                }
            }
        },
        "model.Slot": {
            "type": "object",
            "properties": {
                "endsAt": {
                    "type": "string"
                },
                "id": {
                    "type": "string"
                },
                "isValidated": {
                    "type": "boolean"
                },
                "startsAt": {
                    "type": "string"
                }
            }
        },
        "signin.SigninDto": {
            "type": "object",
            "required": [
                "identifier",
                "password"
            ],
            "properties": {
                "identifier": {
                    "type": "string"
                },
                "password": {
                    "type": "string"
                }
            }
        },
        "signin.TokenResponseDto": {
            "type": "object",
            "properties": {
                "access_token": {
                    "type": "string"
                }
            }
        },
        "slot.ConfirmSlotDto": {
            "type": "object",
            "required": [
                "endsAt",
                "startsAt"
            ],
            "properties": {
                "endsAt": {
                    "type": "string"
                },
                "startsAt": {
                    "type": "string"
                }
            }
        }
    },
    "securityDefinitions": {
        "AccessTokenCookie": {
            "description": "Enter your bearer token in the format **Bearer \u0026lt;token\u0026gt;**",
            "type": "apiKey",
            "name": "access_token",
            "in": "cookie"
        }
    }
}